language_tags/Subtag.py
language_tags/Tag.py
language_tags/__init__.py
language_tags/tags.py
language_tags/data/__init__.py
language_tags/data/json/collection.json
language_tags/data/json/extlang.json
language_tags/data/json/grandfathered.json
language_tags/data/json/index.json
language_tags/data/json/language.json
language_tags/data/json/macrolanguage.json
language_tags/data/json/meta.json
language_tags/data/json/private-use.json
language_tags/data/json/redundant.json
language_tags/data/json/region.json
language_tags/data/json/registry.json
language_tags/data/json/script.json
language_tags/data/json/special.json
language_tags/data/json/variant.json
language_tags-1.2.0.dist-info/LICENSE
language_tags-1.2.0.dist-info/METADATA
language_tags-1.2.0.dist-info/WHEEL
language_tags-1.2.0.dist-info/top_level.txt
language_tags-1.2.0.dist-info/RECORD
