Metadata-Version: 2.1
Name: language_tags
Version: 1.2.0
Summary: This project is a Python version of the language-tags Javascript project.
Home-page: https://github.com/OnroerendErfgoed/language-tags
Author: Flanders Heritage Agency
Author-email: ict@onroerenderfgoed.be
License: MIT
Platform: any
Classifier: Topic :: Software Development :: Libraries :: Python Modules
Classifier: Programming Language :: Python
Classifier: Programming Language :: Python :: 3.8
Classifier: Programming Language :: Python :: 3.9
Classifier: Programming Language :: Python :: 3.10
Classifier: License :: OSI Approved :: MIT License
License-File: LICENSE
